<Object name="PlayerScore">
</Object>

<Object name="Player">
	<Position x="-180" y="125" z="0" />
</Object>

<Object name="ParticleEmiter">
	<Position x="110" y="234" z="0" />
</Object>

<Object name="Ground">
	<Position x="-200" y="200" z="0" />
</Object>

<Object name="Ground2">
	<Position x="50" y="250" z="0" />
</Object>

<Object name="Ground3">
	<Position x="252" y="284" z="0" />
</Object>

<Object name="Ground4">
	<Position x="220" y="180" z="0" />
</Object>

<Object name="Ground5">
	<Position x="300" y="140" z="0" />
</Object>

<Object name="Ground6">
	<Position x="450" y="275" z="0" />
</Object>

<Object name="Ground7">
	<Position x="550" y="275" z="0" />
</Object>

<Object name="Ground8">
	<Position x="420" y="100" z="0" />
</Object>

<Object name="Geyser">
	<Position x="110" y="234" z="0" />
</Object>

<Object name="LevelMusic" />